lemiknow/__init__.py
lemiknow/__main__.py
lemiknow/console_sender.py
lemiknow/desktop_sender.py
lemiknow/discord_sender.py
lemiknow/email_sender.py
lemiknow/matrix_sender.py
lemiknow/slack_sender.py
lemiknow/sms_sender.py
lemiknow/teams_sender.py
lemiknow/telegram_sender.py
lemiknow/tests/__init__.py
lemiknow/tests/test_senders.py
lemiknow-0.1.0.dist-info/LICENSE
lemiknow-0.1.0.dist-info/METADATA
lemiknow-0.1.0.dist-info/WHEEL
lemiknow-0.1.0.dist-info/entry_points.txt
lemiknow-0.1.0.dist-info/top_level.txt
lemiknow-0.1.0.dist-info/RECORD
