Metadata-Version: 2.1
Name: lemiknow
Version: 0.1.0
Summary: Let's you know when your function is called, ends or crashes
Home-page: https://github.com/nachotp/lemiknow
Author: Ignacio Tampe
Author-email: thenachotp@gmail.com
License: MIT
Platform: UNKNOWN
Classifier: Intended Audience :: Developers
Classifier: Development Status :: 3 - Alpha
Classifier: License :: OSI Approved :: MIT License
Classifier: Programming Language :: Python :: 3.6
Classifier: Topic :: Communications
Requires-Python: >=3.6
Requires-Dist: yagmail (>=0.11.214)
Requires-Dist: keyring
Requires-Dist: keyrings.alt (==3.1.1)
Requires-Dist: matrix-client
Requires-Dist: python-telegram-bot
Requires-Dist: requests
Requires-Dist: twilio
